smipoly/__init__.py
smipoly/_version.py
smipoly/rules/excl_lst.json
smipoly/rules/mon_dic.json
smipoly/rules/mon_dic_inv.json
smipoly/rules/mon_lst.json
smipoly/rules/mon_vals.json
smipoly/rules/ps_class.json
smipoly/rules/ps_gen.pkl
smipoly/rules/ps_rxn.pkl
smipoly/smip/__init__.py
smipoly/smip/funclib.py
smipoly/smip/monc.py
smipoly/smip/polg.py
smipoly-1.1.2.dist-info/METADATA
smipoly-1.1.2.dist-info/WHEEL
smipoly-1.1.2.dist-info/licenses/LICENSE
smipoly-1.1.2.dist-info/RECORD
