Metadata-Version: 2.4
Name: smipoly
Version: 1.1.2
Summary: rule-based virtual polymer library generator
Project-URL: Homepage, https://github.com/PEJpOhno/SMiPoly
Project-URL: Issues, https://github.com/PEJpOhno/SMiPoly/issues
Author-email: Mitsuru Ohno <pejpohn@gmail.com>
License: BSD 3-Clause License
License-File: LICENSE
Classifier: Development Status :: 4 - Beta
Classifier: License :: OSI Approved :: BSD License
Classifier: Programming Language :: Python :: 3
Classifier: Topic :: Scientific/Engineering :: Chemistry
Requires-Python: <3.15,>=3.10
Requires-Dist: numpy>=1.26.0
Requires-Dist: pandas>=2.1.0
Requires-Dist: rdkit>=2023.9.1
